MANIFEST.in
README.rst
TODO.rst
requirements.txt
setup.py
PyPT.egg-info/PKG-INFO
PyPT.egg-info/SOURCES.txt
PyPT.egg-info/dependency_links.txt
PyPT.egg-info/entry_points.txt
PyPT.egg-info/pbr.json
PyPT.egg-info/requires.txt
PyPT.egg-info/top_level.txt
pypt/__init__.py
pypt/_version.py
pypt/main.py
pypt/command/__init__.py
pypt/command/config.py
pypt/command/init.py
pypt/git_utils/__init__.py
pypt/git_utils/get_origin.py
pypt/git_utils/git_config.py
pypt/io/__init__.py
pypt/io/temp_file.py
pypt/io/config/__init__.py
pypt/io/config/file.py
pypt/io/config/reader.py
pypt/io/config/writer.py
pypt/parser/__init__.py
pypt/parser/manifest.py
pypt/parser/setup.py
pypt/question/__init__.py
pypt/question/choice.py
pypt/question/question.py
pypt/question/series/__init__.py
pypt/question/series/init.py
pypt/templates/__init__.py
pypt/templates/config/base.j2
pypt/templates/config/init.j2
pypt/templates/init/base.j2
pypt/templates/init/long_description.j2
pypt/templates/init/packages.j2
pypt/templates/init/requirements.j2
pypt/templates/init/setup.j2