Metadata-Version: 1.1
Name: PyPT
Version: 0.6.0
Summary: Python Package Tools
Home-page: https://github.com/jackmaney/pypt
Author: Jack Maney
Author-email: jackmaney@gmail.com
License: MIT
Platform: UNKNOWN
Classifier: Programming Language :: Python :: 2.7
